cicdstatemgr/__init__.py
cicdstatemgr/__main__.py
cicdstatemgr/cicdstatemgr.py
cicdstatemgr/cli.py
cicdstatemgr/jinja2util.py
cicdstatemgr/utils.py
cicdstatemgr/datasources/__init__.py
cicdstatemgr/datasources/idfile.py
cicdstatemgr/datasources/jsonfile.py
cicdstatemgr/datasources/redis.py
cicdstatemgr/datasources/shellfile.py
cicdstatemgr/datasources/yamlfile.py
cicdstatemgr-1.0.0.dist-info/LICENSE
cicdstatemgr-1.0.0.dist-info/METADATA
cicdstatemgr-1.0.0.dist-info/WHEEL
cicdstatemgr-1.0.0.dist-info/entry_points.txt
cicdstatemgr-1.0.0.dist-info/top_level.txt
cicdstatemgr-1.0.0.dist-info/RECORD
