Metadata-Version: 2.1
Name: cicdstatemgr
Version: 1.0.0
Summary: State management utility for CICD systems
Home-page: https://github.com/bitsofinfo/cicdstatemgr
Author: bitsofinfo
Author-email: bitsofinfo.g@gmail.com
License: UNKNOWN
Platform: UNKNOWN
Classifier: Programming Language :: Python :: 3
Classifier: License :: OSI Approved :: MIT License
Classifier: Operating System :: OS Independent
Requires-Python: >=3.8
